onium/__init__.py
onium/__main__.py
onium/asar.py
onium/code.py
onium-0.9.2.dist-info/LICENSE.txt
onium-0.9.2.dist-info/METADATA
onium-0.9.2.dist-info/WHEEL
onium-0.9.2.dist-info/entry_points.txt
onium-0.9.2.dist-info/top_level.txt
onium-0.9.2.dist-info/RECORD
