Metadata-Version: 2.1
Name: onium
Version: 0.9.2
Summary: Onium - Inject hebrew support into a slack desktop app
Home-page: https://github.com/yonatan-mitmit/onium
Author: Yonatan Striem-Amit
Author-email: yonatan@striem-amit.com
Keywords: slack hebrew electron
Classifier: Development Status :: 5 - Production/Stable
Classifier: License :: OSI Approved :: MIT License
Classifier: Programming Language :: Python :: 2
Classifier: Programming Language :: Python :: 2.7
Classifier: Programming Language :: Python :: 3
Classifier: Programming Language :: Python :: 3.4
Classifier: Programming Language :: Python :: 3.5
Classifier: Programming Language :: Python :: 3.6
Classifier: Programming Language :: Python :: 3.7
License-File: LICENSE.txt
Requires-Dist: six
Requires-Dist: colorama
Requires-Dist: psutil
Requires-Dist: requests
